NovalIDE-1.1.8.data/data/noval.ico
NovalIDE-1.1.8.data/data/template.xml
NovalIDE-1.1.8.data/data/version.txt
NovalIDE-1.1.8.data/data/locale/en_US/LC_MESSAGES/novalide.mo
NovalIDE-1.1.8.data/data/locale/zh_CN/LC_MESSAGES/novalide.mo
NovalIDE-1.1.8.data/data/locale/zh_CN/LC_MESSAGES/wxstd.mo
NovalIDE-1.1.8.data/data/locale/zh_CN/LC_MESSAGES/wxstock.mo
NovalIDE-1.1.8.data/data/tkdnd/libtkdnd2.9.2.so
NovalIDE-1.1.8.data/data/tkdnd/pkgIndex.tcl
NovalIDE-1.1.8.data/data/tkdnd/tkdnd.tcl
NovalIDE-1.1.8.data/data/tkdnd/tkdnd_compat.tcl
NovalIDE-1.1.8.data/data/tkdnd/tkdnd_generic.tcl
NovalIDE-1.1.8.data/data/tkdnd/tkdnd_macosx.tcl
NovalIDE-1.1.8.data/data/tkdnd/tkdnd_unix.tcl
NovalIDE-1.1.8.data/data/tkdnd/tkdnd_utils.tcl
NovalIDE-1.1.8.data/data/tkdnd/tkdnd_windows.tcl
dummy/__init__.py
dummy/basedb.py
dummy/sql.py
dummy/userdb.py
noval/__init__.py
noval/autocomplete.py
noval/binds.py
noval/boot_common.py
noval/calltip.py
noval/colorfont.py
noval/constants.py
noval/consts.py
noval/core.py
noval/docoption.py
noval/docposition.py
noval/executable.py
noval/filewatcher.py
noval/frame.py
noval/generalopt.py
noval/ide.py
noval/iface.py
noval/imageutils.py
noval/launcher.py
noval/logview.py
noval/menu.py
noval/misc.py
noval/model.py
noval/newTkDnD.py
noval/outputthread.py
noval/plugin.py
noval/plugin_joint.py
noval/preference.py
noval/process.py
noval/statusbar.py
noval/syntax_themes.py
noval/terminal.py
noval/toolbar.py
noval/ui_base.py
noval/ui_common.py
noval/ui_constants.py
noval/ui_lang.py
noval/ui_utils.py
noval/bmp_source/about.png
noval/bmp_source/clearbk.png
noval/bmp_source/cmd.png
noval/bmp_source/comment.png
noval/bmp_source/custom_init.png
noval/bmp_source/dedent.png
noval/bmp_source/delete.png
noval/bmp_source/doc_props.png
noval/bmp_source/environment.png
noval/bmp_source/exit.png
noval/bmp_source/folder2.png
noval/bmp_source/gotoline.png
noval/bmp_source/help.png
noval/bmp_source/highlighter-text.png
noval/bmp_source/indent.png
noval/bmp_source/linebreak.png
NovalIDE-1.1.8.dist-info/LICENSE.md
NovalIDE-1.1.8.dist-info/METADATA
NovalIDE-1.1.8.dist-info/WHEEL
NovalIDE-1.1.8.dist-info/entry_points.txt
NovalIDE-1.1.8.dist-info/top_level.txt
NovalIDE-1.1.8.dist-info/RECORD
