Metadata-Version: 2.1
Name: NovalIDE
Version: 1.1.8
Summary: NovalIDE is a cross platform Python IDE
Home-page: https://github.com/noval102200/NovalIDE.git
Author: wukan
Author-email: wekay102200@sohu.com
License: Genetalks
Platform: UNKNOWN
Classifier: Development Status :: 4 - Beta
Classifier: Programming Language :: Python
Classifier: Topic :: Software Development :: Libraries :: Python Modules
Classifier: Programming Language :: Python :: 3
Classifier: Programming Language :: Python :: 3.5
Classifier: Programming Language :: Python :: 3.6
Classifier: Programming Language :: Python :: 3.7
Classifier: Programming Language :: Python :: Implementation :: CPython
Classifier: Programming Language :: Python :: Implementation :: PyPy
Requires-Dist: chardet (==3.0.4)
Requires-Dist: future (==0.17.1)
Requires-Dist: Pillow (==6.1.0)
Requires-Dist: psutil (==5.6.3)
Requires-Dist: pyperclip (==1.7.0)
Requires-Dist: requests (==2.22.0)
Requires-Dist: watchdog (==0.9.0)
